{
    "textAnnotations": [
        {
            "nimic": 0
        },
        {
            "description": "JACOBS"
        },
        {
            "description": "Er "
        },
        {
            "description": "Hupizw"
        },
        {
            "description": "va"
        },
        {
            "description": "Vevopal"
        },
        {
            "description": "oialnuBavw"
        },
        {
            "description": "Sacobs"
        },
        {
            "description": "Decedciuao"
        },
        {
            "description": "Torunvion"
        },
        {
            "description": "okot"
        }
    ]
}