{
    "textAnnotations": [
        {
            "nimic": 0
        },
        {
            "description": "Erancho"
        },
        {
            "description": "coFFEE_Shop"
        },
        {
            "description": "AudeST1C\""
        },
        {
            "description": "Dinng  Doom"
        },
        {
            "description": "Mlcucav Rest AURA$"
        },
        {
            "description": "TAQUE]"
        },
        {
            "description": "COMPAD"
        }
    ]
}