{
    "textAnnotations": [
        {
            "nimic": 0
        },
        {
            "description": "CtertioNS"
        },
        {
            "description": "ENTTRAY"
        },
        {
            "description": "mornan"
        },
        {
            "description": "ROBDAENDTY"
        },
        {
            "description": "422s"
        },
        {
            "description": "Lal"
        },
        {
            "description": "REPAIE"
        },
        {
            "description": "Eeea"
        },
        {
            "description": "SHOE"
        },
        {
            "description": "~CLEANERS"
        }
    ]
}