{
    "textAnnotations": [
        {
            "nimic": 0
        },
        {
            "description": "1"
        },
        {
            "description": "BOI"
        },
        {
            "description": "OFEl"
        },
        {
            "description": "T045"
        },
        {
            "description": "Qub"
        },
        {
            "description": "\"oFtIce"
        },
        {
            "description": "DNILY"
        },
        {
            "description": "EROADwL("
        },
        {
            "description": "ICLET"
        }
    ]
}