{
    "textAnnotations": [
        {
            "nimic": 0
        },
        {
            "description": "[ovensor"
        },
        {
            "description": "Wnell"
        },
        {
            "description": "Maepidued Mateild"
        },
        {
            "description": "FNn{aYor Bla"
        },
        {
            "description": "TnMAIL"
        },
        {
            "description": "MqHTLL"
        },
        {
            "description": "TG 0"
        },
        {
            "description": "MIOMpolt"
        },
        {
            "description": "DS7TTHIutLLS"
        },
        {
            "description": "TtSTa Tue4"
        }
    ]
}