{
    "textAnnotations": [
        {
            "nimic": 0
        },
        {
            "description": "Ihr,"
        },
        {
            "description": "WL"
        },
        {
            "description": "OUR OWM"
        },
        {
            "description": "UGleaning "
        },
        {
            "description": "REPAIR"
        },
        {
            "description": "DoNe ON."
        },
        {
            "description": "SPBEMISES"
        },
        {
            "description": "LEATHEI"
        },
        {
            "description": "CLI"
        },
        {
            "description": "E.ni}y("
        },
        {
            "description": "CLEANERS'"
        },
        {
            "description": "AHR)"
        },
        {
            "description": "'PRICE "
        },
        {
            "description": "IHRIFIY"
        },
        {
            "description": "\"REASOMABLE "
        },
        {
            "description": "1PLANT E"
        },
        {
            "description": "ME MPRATE \u20ac"
        },
        {
            "description": "ALTERATIC"
        }
    ]
}