{
    "textAnnotations": [
        {
            "nimic": 0
        },
        {
            "description": "YO"
        },
        {
            "description": "MERCANTILE"
        },
        {
            "description": "CIRCASJE"
        },
        {
            "description": "NEW"
        },
        {
            "description": "OLI"
        },
        {
            "description": "STUI"
        },
        {
            "description": "Eues"
        },
        {
            "description": "CE "
        },
        {
            "description": "UUPPLIES"
        },
        {
            "description": "~SUNDI"
        },
        {
            "description": "FAX"
        },
        {
            "description": "SECO"
        },
        {
            "description": "ARRC"
        },
        {
            "description": "WARE"
        },
        {
            "description": "HOLD"
        }
    ]
}