{
    "textAnnotations": [
        {
            "nimic": 0
        },
        {
            "description": "IESb"
        },
        {
            "description": "ETTD"
        },
        {
            "description": "Ouans"
        },
        {
            "description": "BuS"
        },
        {
            "description": "G"
        },
        {
            "description": "Ouols"
        },
        {
            "description": "CHILL"
        },
        {
            "description": "ALrAN"
        },
        {
            "description": "Jac Ginme"
        },
        {
            "description": "ESE"
        },
        {
            "description": "6"
        },
        {
            "description": ""
        }
    ]
}