{
    "textAnnotations": [
        {
            "nimic": 0
        },
        {
            "description": "203 3a| EsCoRIIL"
        },
        {
            "description": "ER"
        },
        {
            "description": "Eiquenr"
        },
        {
            "description": "Homow"
        },
        {
            "description": "#CYOL"
        },
        {
            "description": "FonA"
        },
        {
            "description": "Uce "
        },
        {
            "description": "TuL"
        },
        {
            "description": "Sle"
        },
        {
            "description": "Kcer"
        },
        {
            "description": "Grong HLmncEteR"
        },
        {
            "description": "(AAR"
        },
        {
            "description": "alpvetizer"
        }
    ]
}