{
    "textAnnotations": [
        {
            "nimic": 0
        },
        {
            "description": "bzorgen bij"
        },
        {
            "description": "huryin"
        },
        {
            "description": "arall"
        },
        {
            "description": "Wml MMAAAF"
        },
        {
            "description": "nenien I IU min"
        },
        {
            "description": "PIZZAI"
        },
        {
            "description": "~TAR"
        },
        {
            "description": "pecidieii"
        },
        {
            "description": "Te2052 4"
        }
    ]
}