{
    "textAnnotations": [
        {
            "nimic": 0
        },
        {
            "description": "Dud2erla"
        },
        {
            "description": "Qods"
        },
        {
            "description": "IcuoiT9fn|"
        },
        {
            "description": "Nin/ 2()"
        },
        {
            "description": "9576 )  /; |"
        },
        {
            "description": "THYaser"
        },
        {
            "description": "{k]"
        },
        {
            "description": "TTW.."
        },
        {
            "description": "Suro"
        }
    ]
}