{
    "textAnnotations": [
        {
            "nimic": 0
        },
        {
            "description": "ENGINEERI"
        },
        {
            "description": "Rpuna ? Minnyo"
        },
        {
            "description": "JTECH QUTO REPHR"
        },
        {
            "description": "Jurd"
        },
        {
            "description": "LL4NI"
        },
        {
            "description": "2"
        },
        {
            "description": "712 42-4"
        },
        {
            "description": "Louze Sc-"
        },
        {
            "description": "AUTO REPAIR"
        },
        {
            "description": "JAVI FLAT FIhED"
        },
        {
            "description": "Koid"
        },
        {
            "description": "FTEI"
        },
        {
            "description": "Ed"
        },
        {
            "description": "E 112 St; Harlem NYC"
        },
        {
            "description": "Hauare"
        },
        {
            "description": "MUIV RRFPAR }"
        },
        {
            "description": "oad?"
        }
    ]
}