{
    "textAnnotations": [
        {
            "nimic": 0
        },
        {
            "description": "8052"
        },
        {
            "description": "HJMUS"
        },
        {
            "description": "LUNck"
        },
        {
            "description": "Jjiy"
        },
        {
            "description": "SF EcLAL"
        },
        {
            "description": "Umaq"
        },
        {
            "description": "PRIME"
        },
        {
            "description": "A1A"
        },
        {
            "description": "Ri"
        },
        {
            "description": "90"
        },
        {
            "description": "Di?"
        }
    ]
}