{
    "textAnnotations": [
        {
            "nimic": 0
        },
        {
            "description": "STAATUICHE"
        },
        {
            "description": "ZEITUNGEN -"
        },
        {
            "description": "SPIRITUOSEN"
        },
        {
            "description": "TABAKWAREN"
        },
        {
            "description": "LOTTERIE EINNAHME"
        },
        {
            "description": "GeschenRARaKSaRTiKEL"
        },
        {
            "description": "Lono"
        },
        {
            "description": "TMarlboro"
        },
        {
            "description": "LO"
        },
        {
            "description": "Lono"
        },
        {
            "description": "'ZEMSCHRIFTEN"
        }
    ]
}