{
    "textAnnotations": [
        {
            "nimic": 0
        },
        {
            "description": "Samitany"
        },
        {
            "description": "SHop"
        },
        {
            "description": "BARBER"
        },
        {
            "description": "CIOSED"
        },
        {
            "description": "SHOP"
        },
        {
            "description": "ERS WILL BE"
        },
        {
            "description": "ED AWAY"
        },
        {
            "description": "YEASE Do KIT"
        },
        {
            "description": "Davaa"
        },
        {
            "description": "BARBER `"
        },
        {
            "description": "cusi04fa"
        }
    ]
}