{
    "textAnnotations": [
        {
            "nimic": 0
        },
        {
            "description": "MOVIES 47"
        },
        {
            "description": "INFO"
        },
        {
            "description": "CALL"
        },
        {
            "description": "9060"
        },
        {
            "description": "Il0 310 510 720"
        },
        {
            "description": "920"
        },
        {
            "description": "FEAR dOT COM"
        },
        {
            "description": "130"
        },
        {
            "description": "340 730"
        },
        {
            "description": "940"
        },
        {
            "description": "SiGnS"
        },
        {
            "description": "910"
        },
        {
            "description": "SPY KIDS 2"
        },
        {
            "description": "pe]"
        },
        {
            "description": "120"
        },
        {
            "description": "710"
        },
        {
            "description": "930"
        },
        {
            "description": "TRIPLE X"
        }
    ]
}