{
    "textAnnotations": [
        {
            "nimic": 0
        },
        {
            "description": "CXLEDOMAM"
        },
        {
            "description": "Mntrn"
        },
        {
            "description": "QUALITY DRY CLEANERS"
        },
        {
            "description": "GENERAL STORE"
        },
        {
            "description": "LICENCE"
        },
        {
            "description": "RFPAIKC"
        },
        {
            "description": "ALIFRATIOY"
        },
        {
            "description": "FOOD"
        },
        {
            "description": "WINE"
        },
        {
            "description": "Ort"
        }
    ]
}