{
    "textAnnotations": [
        {
            "nimic": 0
        },
        {
            "description": "GLAD"
        },
        {
            "description": "nnn"
        },
        {
            "description": "W]"
        },
        {
            "description": "Mabrook"
        },
        {
            "description": ")rubietia"
        },
        {
            "description": "SALES"
        },
        {
            "description": "RVICE"
        },
        {
            "description": "SONY"
        },
        {
            "description": "6416"
        },
        {
            "description": "103-763.370 _"
        }
    ]
}