{
    "textAnnotations": [
        {
            "nimic": 0
        },
        {
            "description": "ERAI"
        },
        {
            "description": "Torr"
        },
        {
            "description": "Williams"
        },
        {
            "description": "Or"
        },
        {
            "description": "gon"
        },
        {
            "description": "est: 1897"
        },
        {
            "description": "ele"
        },
        {
            "description": "'.1375 ft"
        }
    ]
}