{
    "textAnnotations": [
        {
            "nimic": 0
        },
        {
            "description": "LINENS"
        },
        {
            "description": "shdEs"
        },
        {
            "description": "A"
        },
        {
            "description": "D@"
        },
        {
            "description": "cldtheS"
        },
        {
            "description": "BIG CLoSET resleishdp"
        },
        {
            "description": "60108"
        },
        {
            "description": "18"
        },
        {
            "description": "KItcheh"
        },
        {
            "description": "MI"
        },
        {
            "description": "BIG_CLOSET"
        },
        {
            "description": "'BZALE Sck"
        },
        {
            "description": "Cloins %745 rots"
        }
    ]
}