{
    "textAnnotations": [
        {
            "nimic": 0
        },
        {
            "description": "BIK '"
        },
        {
            "description": "DINNR"
        },
        {
            "description": "STOP)"
        },
        {
            "description": "Booth"
        },
        {
            "description": "Eornu"
        },
        {
            "description": "Mliss Jllorcester"
        },
        {
            "description": "SirVmIC"
        },
        {
            "description": "~nontis"
        }
    ]
}