{
    "textAnnotations": [
        {
            "nimic": 0
        },
        {
            "description": "40"
        },
        {
            "description": "MOTEL"
        },
        {
            "description": "Dog"
        },
        {
            "description": "SaW A sigh"
        },
        {
            "description": "THAT"
        },
        {
            "description": "SAA"
        },
        {
            "description": "WET PAINE"
        },
        {
            "description": "50 _ HELDID"
        }
    ]
}