{
    "textAnnotations": [
        {
            "nimic": 0
        },
        {
            "description": "Peinde @lMja_4"
        },
        {
            "description": "Pue"
        },
        {
            "description": "Poppv Pz_Horly"
        },
        {
            "description": "#E^?"
        },
        {
            "description": "OweaEAZ"
        },
        {
            "description": "Worldwile No./"
        },
        {
            "description": "Choice 0}"
        },
        {
            "description": "Veteriliaians"
        },
        {
            "description": "Ar tana"
        },
        {
            "description": "@e"
        },
        {
            "description": "Hd"
        },
        {
            "description": "Oldin"
        }
    ]
}