{
    "textAnnotations": [
        {
            "nimic": 0
        },
        {
            "description": "Till"
        },
        {
            "description": "CREDIT ["
        },
        {
            "description": "{ CARDS /"
        },
        {
            "description": "12.PM"
        },
        {
            "description": "3 AND FOREIGN`"
        },
        {
            "description": "CURRENCY _"
        },
        {
            "description": "'DAYS A WEEK\""
        },
        {
            "description": "X accepTed"
        },
        {
            "description": "N 9.AM"
        }
    ]
}