{
    "textAnnotations": [
        {
            "nimic": 0
        },
        {
            "description": "pbos"
        },
        {
            "description": "cordc"
        },
        {
            "description": "ANCHOR"
        },
        {
            "description": "GoLp"
        },
        {
            "description": "Vizcik"
        },
        {
            "description": "LACK CAt"
        },
        {
            "description": "IREE "
        },
        {
            "description": "Shoi"
        },
        {
            "description": "Eicaret"
        },
        {
            "description": "I#RANKIYAR"
        },
        {
            "description": "WRH"
        },
        {
            "description": "Three"
        },
        {
            "description": "Waa"
        },
        {
            "description": "SPEARS"
        },
        {
            "description": "ESN"
        },
        {
            "description": "Top"
        },
        {
            "description": "SCORF"
        },
        {
            "description": "200 cicap"
        },
        {
            "description": "MEDIUI"
        },
        {
            "description": "(rOSEMARY"
        },
        {
            "description": "GoldeLi"
        },
        {
            "description": "Eee_"
        },
        {
            "description": "~NAVY CuI"
        },
        {
            "description": "carn "
        },
        {
            "description": "11C\""
        },
        {
            "description": "GOLD FLAKE"
        },
        {
            "description": "CAPSTAN"
        },
        {
            "description": "VEnoue"
        },
        {
            "description": "AcnpBuA"
        },
        {
            "description": "DODIALLE"
        },
        {
            "description": "CLUBS"
        },
        {
            "description": "udia"
        },
        {
            "description": "tualecee"
        },
        {
            "description": "FLAKE"
        },
        {
            "description": "PASSING"
        }
    ]
}